chj_saih/__init__.py
chj_saih/config.py
chj_saih/data_fetcher.py
chj_saih/exceptions.py
chj_saih/sensors.py
chj_saih-0.2.2.dist-info/METADATA
chj_saih-0.2.2.dist-info/WHEEL
chj_saih-0.2.2.dist-info/entry_points.txt
chj_saih-0.2.2.dist-info/top_level.txt
chj_saih-0.2.2.dist-info/RECORD
